prismatui/__init__.py
prismatui/_backend/__init__.py
prismatui/_backend/backend.py
prismatui/_backend/backend_curses.py
prismatui/_backend/constants.py
prismatui/_components/__init__.py
prismatui/_components/layer.py
prismatui/_components/pixel.py
prismatui/_components/section.py
prismatui/_components/terminal.py
prismatui/_misc/__init__.py
prismatui/_misc/blend_mode.py
prismatui/_misc/palette.py
prismatui/_misc/parser_pri.py
prismatui/_utils/__init__.py
prismatui/_utils/debug_logger.py
prismatui/_utils/mosaic_parser.py
prismatui-0.3.0.dist-info/licenses/LICENSE
prismatui-0.3.0.dist-info/METADATA
prismatui-0.3.0.dist-info/WHEEL
prismatui-0.3.0.dist-info/top_level.txt
prismatui-0.3.0.dist-info/RECORD
