Metadata-Version: 2.4
Name: prismatui
Version: 0.3.0
Summary: A TUI framework based on the idea of "multi-layered transparency" composition.
Home-page: https://github.com/diegobarmor/prismatui
Author: DiegoBarMor
Author-email: diegobarmor42@gmail.com
License: MIT
Keywords: tui terminal user interface transparency layers layered curses
Classifier: Programming Language :: Python :: 3
Classifier: License :: OSI Approved :: MIT License
Classifier: Operating System :: OS Independent
Requires-Python: >=3.10
License-File: LICENSE
Dynamic: author
Dynamic: author-email
Dynamic: classifier
Dynamic: description
Dynamic: description-content-type
Dynamic: home-page
Dynamic: keywords
Dynamic: license
Dynamic: license-file
Dynamic: requires-python
Dynamic: summary
